handsome
tests
